{
	"name": "DelimitedText3",
	"properties": {
		"linkedServiceName": {
			"referenceName": "ls_sql_archive",
			"type": "LinkedServiceReference"
		},
		"annotations": [],
		"type": "DelimitedText",
		"typeProperties": {
			"location": {
				"type": "AzureBlobStorageLocation",
				"fileName": "emp_text (2).txt",
				"folderPath": "customer",
				"container": "landing"
			},
			"columnDelimiter": ",",
			"escapeChar": "\\",
			"firstRowAsHeader": true,
			"quoteChar": "\""
		},
		"schema": [
			{
				"name": "Name",
				"type": "String"
			},
			{
				"name": "Father",
				"type": "String"
			},
			{
				"name": "Village",
				"type": "String"
			},
			{
				"name": "Age",
				"type": "String"
			}
		]
	}
}